kmt/__init__.py
kmt/__main__.py
kmt/cli.py
kmt/core.py
kmt/exception.py
kmt/j2support.py
kmt/pipeline_support.py
kmt/step_handlers.py
kmt/step_support.py
kmt/util.py
kmt/yaml_types.py
kmt-0.3.6.dist-info/licenses/LICENSE
kmt-0.3.6.dist-info/METADATA
kmt-0.3.6.dist-info/WHEEL
kmt-0.3.6.dist-info/entry_points.txt
kmt-0.3.6.dist-info/top_level.txt
kmt-0.3.6.dist-info/RECORD
