Metadata-Version: 2.4
Name: kmt
Version: 0.3.6
Summary: Kubernetes Manifest Transform
Home-page: https://github.com/archmachina/kmt
Download-URL: https://pypi.org/project/kmt/
Author: Jesse Reichman
License: MIT
Keywords: Kubernetes,Manifest,Transform
License-File: LICENSE
Requires-Dist: PyYAML>=6.0.0
Requires-Dist: Jinja2>=3.1.0
Requires-Dist: jsonpatch>=1.33
Requires-Dist: jsonpath-ng>=1.6.1
Dynamic: author
Dynamic: description
Dynamic: description-content-type
Dynamic: download-url
Dynamic: home-page
Dynamic: keywords
Dynamic: license
Dynamic: license-file
Dynamic: requires-dist
Dynamic: summary
